README.md
setup.py
bingdog/__init__.py
bingdog/appconfig.py
bingdog/executor.py
bingdog/logger.py
bingdog/task.py
bingdog/taskhandler.py
bingdog/taskproxy.py
bingdog/taskutil.py
bingdog/util.py
bingdog.egg-info/PKG-INFO
bingdog.egg-info/SOURCES.txt
bingdog.egg-info/dependency_links.txt
bingdog.egg-info/top_level.txt