Metadata-Version: 2.1
Name: bingdog
Version: 0.1.1
Summary: An implementation of daynamic proxy
Home-page: https://github.com/sherocktong/bingdog
Author: Thomas Tong
Author-email: k.thomas.tong@gmail.com
License: UNKNOWN
Platform: UNKNOWN
Classifier: Programming Language :: Python :: 3
Classifier: License :: OSI Approved :: MIT License
Classifier: Operating System :: OS Independent
Requires-Python: >=3.5
